jocassid_commons/__init__.py
jocassid_commons/accumulator_dict.py
jocassid_commons/data_structures.py
jocassid_commons/dirf.py
jocassid_commons/json.py
jocassid_commons/string.py
jocassid_commons-0.0.8.dist-info/METADATA
jocassid_commons-0.0.8.dist-info/WHEEL
jocassid_commons-0.0.8.dist-info/licenses/LICENSE
jocassid_commons-0.0.8.dist-info/RECORD
